{"0": "cabinet_25", "1": "pillar_26", "2": "cabinet_27", "3": "paper stack_28", "4": "pillar_29", "5": "box_30", "6": "monitor_31", "7": "monitor_32", "8": "monitor_33", "9": "monitor_34", "10": "desk_35", "11": "file cabinet_36", "12": "file cabinet_37", "13": "file cabinet_38", "14": "file cabinet_39", "15": "garbage_40", "16": "bag_41", "17": "backpack_42", "18": "box_43", "19": "box_44", "20": "monitor_45", "21": "monitor_46", "22": "monitor_47", "23": "monitor_48", "24": "keyboard_49", "25": "monitor_50", "26": "wall_51", "27": "ceiling_52", "28": "wall_53", "29": "chair_54", "30": "chair_55", "31": "clutter_56", "32": "clutter_57", "33": "light_66", "34": "box_68", "35": "box_69", "36": "box_70", "37": "box_71", "38": "box_72", "39": "wall_73", "40": "wall_74", "41": "pipe_75", "42": "pipe_76", "43": "pipe_77", "44": "pipe_79", "45": "box_84", "46": "chair_58", "47": "garbage_59", "48": "clutter_60", "49": "clutter_61", "50": "chair_62", "51": "box_63", "52": "wall_64", "53": "box_65", "54": "floor_1", "55": "wall_2", "56": "wall_3", "57": "wall_4", "58": "window_5", "59": "window_6", "60": "counter_7", "61": "heater_8", "62": "heater_9", "63": "heater_10", "64": "bag_12", "65": "desk_13", "66": "garbage_14", "67": "chair_15", "68": "keyboard_16", "69": "monitor_17", "70": "monitor_18", "71": "laptop_19", "72": "device_20", "73": "box_21", "74": "box_22", "75": "box_23", "76": "pillar_24"}