{"0": "desk_0", "1": "curtain_1", "2": "wardrobe closet_2", "3": "shelf_3", "4": "floor_4", "5": "mini fridge_5", "6": "coffee table_6", "7": "chair_7", "8": "dresser_8", "9": "laundry hamper_9", "10": "door_10", "11": "ceiling_11", "12": "wall_12", "13": "doorframe_13", "14": "mirror_14", "15": "towel_15", "16": "towel_16", "17": "soap bottle_17", "18": "object_18", "19": "sink_19", "20": "trash can_20", "21": "wall_21", "22": "picture_22", "23": "object_23", "24": "person_24", "25": "loft bed_25", "26": "backpack_26", "27": "clothes_27", "28": "chair_28", "29": "bag_29", "30": "computer tower_30", "31": "shoes_31", "32": "shelf_32", "33": "chair_33", "34": "monitor_34", "35": "monitor_35", "36": "wall_36", "37": "picture_37", "38": "trash can_38", "39": "ladder_39", "40": "window_40", "41": "clothing_41", "42": "chair_42", "43": "monitor_43", "44": "pillow_44", "45": "water pitcher_45", "46": "bowl_46", "47": "pillow_47", "48": "couch_48", "49": "shelf_49", "50": "wall_50", "51": "radiator_51", "52": "desk_52", "53": "decoration_53"}