{"0": "floor_1", "1": "table_2", "2": "chair_3", "3": "chair_4", "4": "chair_5", "5": "chair_6", "6": "chair_7", "7": "bench_8", "8": "lamp_9", "9": "lamp_10", "10": "wall_11", "11": "cabinet_12", "12": "wall_13", "13": "wall_14", "14": "wall_17", "15": "door_18", "16": "ceiling_20", "17": "pin board wall_21", "18": "pin board wall_22", "19": "wall_24", "20": "picture_27", "21": "picture_28", "22": "wall_29", "23": "wall_30", "24": "plant_32", "25": "kitchen counter_33", "26": "wall_41", "27": "kitchen hood_35", "28": "plant_37", "29": "box_38", "30": "lamp_40", "31": "trash can_43", "32": "backpack_49", "33": "laptop_50"}