{"0": "door_32", "1": "items_34", "2": "floor_1", "3": "door_2", "4": "wall_3", "5": "wall_4", "6": "curtain_5", "7": "curtain_6", "8": "window_7", "9": "lamp_8", "10": "backpack_9", "11": "garbage_10", "12": "desk_11", "13": "chair_12", "14": "bag_100", "15": "wall_14", "16": "frame_15", "17": "air conditioner_16", "18": "wall_17", "19": "frame_18", "20": "bed_19", "21": "pillow_20", "22": "pillow_21", "23": "bedside table_22", "24": "dressing table_23", "25": "ceiling_24", "26": "pillow_25", "27": "clothes_26", "28": "pillow_27", "29": "pillow_28", "30": "lamp_29", "31": "item_30"}