{"0": "window_0", "1": "window_1", "2": "table_2", "3": "kitchen counter_3", "4": "shower_4", "5": "curtain_5", "6": "curtain_6", "7": "desk_7", "8": "cabinet_8", "9": "floor_9", "10": "sink_10", "11": "scale_11", "12": "trash can_12", "13": "trash can_13", "14": "trash can_14", "15": "tv_15", "16": "pillow_16", "17": "clock_17", "18": "backpack_18", "19": "wall_19", "20": "wall_20", "21": "wall_21", "22": "wall_22", "23": "wall_23", "24": "wall_24", "25": "wall_25", "26": "wall_26", "27": "wall_27", "28": "stool_28", "29": "stool_29", "30": "stool_30", "31": "stool_31", "32": "couch_32", "33": "refrigerator_33", "34": "coffee table_34", "35": "table_35", "36": "toilet_36", "37": "bed_37", "38": "cabinet_38", "39": "cabinet_39", "40": "kitchen cabinets_40", "41": "cabinet_41", "42": "cabinet_42", "43": "kitchen cabinets_43", "44": "object_44", "45": "toaster oven_45", "46": "laundry basket_46", "47": "guitar_47", "48": "tissue box_48", "49": "nightstand_49", "50": "nightstand_50", "51": "dish rack_51", "52": "microwave_52", "53": "toaster_53", "54": "door_54", "55": "ceiling_55", "56": "shelf_56", "57": "bicycle_57", "58": "shoes_58", "59": "object_59", "60": "object_60", "61": "object_61", "62": "object_62", "63": "doorframe_63", "64": "mirror_64", "65": "doorframe_65", "66": "guitar case_66"}